VmorpheusVoice/__init__.py
VmorpheusVoice/__main__.py
VmorpheusVoice/main.py
VmorpheusVoice/core/audio/Microphone.py
VmorpheusVoice/core/audio/__init__.py
VmorpheusVoice/tools/Console.py
VmorpheusVoice/tools/Listener_keys.py
VmorpheusVoice/tools/Name_files.py
VmorpheusVoice/tools/Profile.py
VmorpheusVoice/tools/__init__.py
VmorpheusVoice-0.0.1.dist-info/METADATA
VmorpheusVoice-0.0.1.dist-info/WHEEL
VmorpheusVoice-0.0.1.dist-info/entry_points.txt
VmorpheusVoice-0.0.1.dist-info/top_level.txt
VmorpheusVoice-0.0.1.dist-info/RECORD
